odoo8_addon_disable_openerp_online-8.0.1.1.0.99.dev19-py3.8-nspkg.pth
odoo_addons/disable_openerp_online/__init__.py
odoo_addons/disable_openerp_online/__openerp__.py
odoo_addons/disable_openerp_online/data/ir_cron.xml
odoo_addons/disable_openerp_online/i18n/am.po
odoo_addons/disable_openerp_online/i18n/ar.po
odoo_addons/disable_openerp_online/i18n/bg.po
odoo_addons/disable_openerp_online/i18n/bs.po
odoo_addons/disable_openerp_online/i18n/ca.po
odoo_addons/disable_openerp_online/i18n/ca_ES.po
odoo_addons/disable_openerp_online/i18n/cs.po
odoo_addons/disable_openerp_online/i18n/da.po
odoo_addons/disable_openerp_online/i18n/de.po
odoo_addons/disable_openerp_online/i18n/disable_openerp_online.pot
odoo_addons/disable_openerp_online/i18n/el_GR.po
odoo_addons/disable_openerp_online/i18n/en_GB.po
odoo_addons/disable_openerp_online/i18n/es.po
odoo_addons/disable_openerp_online/i18n/es_AR.po
odoo_addons/disable_openerp_online/i18n/es_CL.po
odoo_addons/disable_openerp_online/i18n/es_CO.po
odoo_addons/disable_openerp_online/i18n/es_CR.po
odoo_addons/disable_openerp_online/i18n/es_DO.po
odoo_addons/disable_openerp_online/i18n/es_EC.po
odoo_addons/disable_openerp_online/i18n/es_ES.po
odoo_addons/disable_openerp_online/i18n/es_MX.po
odoo_addons/disable_openerp_online/i18n/es_PE.po
odoo_addons/disable_openerp_online/i18n/es_PY.po
odoo_addons/disable_openerp_online/i18n/es_VE.po
odoo_addons/disable_openerp_online/i18n/et.po
odoo_addons/disable_openerp_online/i18n/eu.po
odoo_addons/disable_openerp_online/i18n/fa.po
odoo_addons/disable_openerp_online/i18n/fi.po
odoo_addons/disable_openerp_online/i18n/fr.po
odoo_addons/disable_openerp_online/i18n/fr_CA.po
odoo_addons/disable_openerp_online/i18n/fr_CH.po
odoo_addons/disable_openerp_online/i18n/gl.po
odoo_addons/disable_openerp_online/i18n/he.po
odoo_addons/disable_openerp_online/i18n/hr.po
odoo_addons/disable_openerp_online/i18n/hr_HR.po
odoo_addons/disable_openerp_online/i18n/hu.po
odoo_addons/disable_openerp_online/i18n/id.po
odoo8_addon_disable_openerp_online-8.0.1.1.0.99.dev19.dist-info/METADATA
odoo8_addon_disable_openerp_online-8.0.1.1.0.99.dev19.dist-info/WHEEL
odoo8_addon_disable_openerp_online-8.0.1.1.0.99.dev19.dist-info/namespace_packages.txt
odoo8_addon_disable_openerp_online-8.0.1.1.0.99.dev19.dist-info/top_level.txt
odoo8_addon_disable_openerp_online-8.0.1.1.0.99.dev19.dist-info/RECORD
